moneta/__init__.py
moneta/admin.py
moneta/apps.py
moneta/forms.py
moneta/models.py
moneta/schemas.py
moneta/signals.py
moneta/tests.py
moneta/urls.py
moneta/utils.py
moneta/views.py
moneta/configuration/__init__.py
moneta/configuration/config.py
moneta/configuration/soap_client.py
moneta/configuration/url_generator.py
moneta/fixtures/payment_systems.json
moneta/management/commands/load_payment_systems.py
moneta/migrations/0001_initial.py
moneta/migrations/0002_load_payment_systems.py
moneta/migrations/0003_auto_20210530_1400.py
moneta/migrations/0004_auto_20210616_1135.py
moneta/migrations/__init__.py
moneta/templates/main.html
moneta/templates/moneta/fail.html
moneta/templates/moneta/init.html
moneta/templates/moneta/success.html
django_payanyway-0.3.2.dist-info/LICENSE
django_payanyway-0.3.2.dist-info/METADATA
django_payanyway-0.3.2.dist-info/WHEEL
django_payanyway-0.3.2.dist-info/top_level.txt
django_payanyway-0.3.2.dist-info/RECORD
