Metadata-Version: 2.1
Name: django-payanyway
Version: 0.3.2
Summary: Moneta(PayAnyWay)
Home-page: https://github.com/r-pletnev/django-moneta
Author: Roman Pletnev
Author-email: ge52@mail.ru
License: GPL
Platform: UNKNOWN
License-File: LICENSE
Requires-Dist: django (>=2)
Requires-Dist: pydantic
Requires-Dist: zeep
Requires-Dist: pydash
Provides-Extra: dev
Requires-Dist: ipython ; extra == 'dev'
Requires-Dist: pytest-django ; extra == 'dev'
Requires-Dist: pytest ; extra == 'dev'
Requires-Dist: pytest-dotenv ; extra == 'dev'
Provides-Extra: test
Requires-Dist: pytest-django ; extra == 'test'
Requires-Dist: pytest ; extra == 'test'
Requires-Dist: pytest-dotenv ; extra == 'test'
